neocortex/__init__.py
neocortex/app.py
neocortex/config.py
neocortex/configtest.py
neocortex/extensions.py
neocortex/manage.py
neocortex/wsgi.py
neocortex/api/__init__.py
neocortex/api/urls.py
neocortex/api/views.py
neocortex/api/client/__init__.py
neocortex/api/client/base.py
neocortex/api/resources/__init__.py
neocortex/api/resources/neurotransmitter.py
neocortex/api/resources/query.py
neocortex/api/resources/user.py
neocortex/auth/__init__.py
neocortex/auth/views.py
neocortex/cli/__init__.py
neocortex/cli/manage.py
neocortex/cli/plugins/__init__.py
neocortex/cli/plugins/config/__init__.py
neocortex/cli/plugins/config/commands.py
neocortex/cli/plugins/config/configfile.py
neocortex/cli/plugins/query/__init__.py
neocortex/cli/plugins/query/commands.py
neocortex/commons/__init__.py
neocortex/commons/pagination.py
neocortex/models/__init__.py
neocortex/models/graph.py
neocortex/models/user.py
neocortex-0.0.1.dist-info/LICENSE
neocortex-0.0.1.dist-info/METADATA
neocortex-0.0.1.dist-info/WHEEL
neocortex-0.0.1.dist-info/entry_points.txt
neocortex-0.0.1.dist-info/top_level.txt
neocortex-0.0.1.dist-info/RECORD
