Metadata-Version: 2.1
Name: neocortex
Version: 0.0.1
Summary: UNKNOWN
Home-page: https://github.com/tjbanks/neocortex
Author: Tyler Banks
Author-email: tbanks@mail.missouri.edu
License: MIT
Platform: UNKNOWN
Classifier: Intended Audience :: Developers
Classifier: Intended Audience :: Education
Classifier: Intended Audience :: Science/Research
Classifier: License :: OSI Approved :: MIT License
Classifier: Programming Language :: Python :: 3
Classifier: Programming Language :: Python :: 3.6
Classifier: Topic :: Software Development :: Libraries
Classifier: Topic :: Software Development :: Libraries :: Python Modules
Classifier: Operating System :: OS Independent
Requires-Dist: click-plugins
Requires-Dist: clint
Requires-Dist: configparser
Requires-Dist: flask
Requires-Dist: flask-sqlalchemy
Requires-Dist: flask-restful
Requires-Dist: flask-migrate
Requires-Dist: flask-jwt-extended
Requires-Dist: tornado (==4.5.2)
Requires-Dist: flask-marshmallow
Requires-Dist: marshmallow-sqlalchemy
Requires-Dist: python-dotenv
Requires-Dist: passlib
Requires-Dist: questionary
Requires-Dist: tox
Requires-Dist: twython
Requires-Dist: webargs
Requires-Dist: py2neo
Requires-Dist: neo4j-driver
Requires-Dist: flask-neo4j4
